{
  "명령부": {
    "출장": [
      {
          "순번": "1",
          "구분": "(소속평가사·직원)",
          "기간": "2025-07-31",
          "제목": "2025년 07월 31일 Thursday",
          "조사자": "이충헌",
          "출장일자": "25/08/01∼08/02",
          "출장목적": "DA241-061362;(제1금융 담보)",
          "출장지역": "충청남도 당진시 송악읍 고대리 346-6",
          "비고": "숙박"
      },
      {
          "순번": "2",
          "구분": "(소속평가사·직원)",
          "기간": "2025-07-31",
          "제목": "2025년 07월 31일 Thursday",
          "조사자": "김도안",
          "출장일자": "25/08/01∼08/02",
          "출장목적": "DA241-061362;(제1금융 담보)",
          "출장지역": "충청남도 당진시 송악읍 고대리 346-6",
          "비고": "숙박"
      },
      {
          "순번": "3",
          "구분": "(소속평가사·직원)",
          "기간": "2025-07-31",
          "제목": "2025년 07월 31일 Thursday",
          "조사자": "문기호",
          "출장일자": "25/08/01",
          "출장목적": "DA251-073002;(주택도시기금(정식))",
          "출장지역": "서울특별시 성동구 행당동 313-30외 행당더힐",
          "비고": "시내"
      },
      {
          "순번": "4",
          "구분": "(소속평가사·직원)",
          "기간": "2025-07-31",
          "제목": "2025년 07월 31일 Thursday",
          "조사자": "장유안",
          "출장일자": "25/08/01",
          "출장목적": "DA251-073003;(협동조합 담보)",
          "출장지역": "인천광역시 남동구 만수동 967-8 거산빌딩",
          "비고": "시외"
      },
      {
          "순번": "5",
          "구분": "(소속평가사·직원)",
          "기간": "2025-07-31",
          "제목": "2025년 07월 31일 Thursday",
          "조사자": "나영준",
          "출장일자": "25/08/01",
          "출장목적": "DA251-073003;(협동조합 담보)",
          "출장지역": "인천광역시 남동구 만수동 967-8 거산빌딩",
          "비고": "시외"
      },
      {
          "순번": "6",
          "구분": "(소속평가사·직원)",
          "기간": "2025-07-31",
          "제목": "2025년 07월 31일 Thursday",
          "조사자": "윤권채",
          "출장일자": "25/08/01",
          "출장목적": "DA251-073013;(제1금융 담보)",
          "출장지역": "경기도 안성시 미양면 개정리 154-9외",
          "비고": "시외"
      },
      {
          "순번": "7",
          "구분": "(소속평가사·직원)",
          "기간": "2025-07-31",
          "제목": "2025년 07월 31일 Thursday",
          "조사자": "나영준",
          "출장일자": "25/08/01",
          "출장목적": "DA251-073109;(제1금융 담보)",
          "출장지역": "서울특별시 마포구 신수동 93-213",
          "비고": "시내"
      },
      {
          "순번": "8",
          "구분": "(소속평가사·직원)",
          "기간": "2025-07-31",
          "제목": "2025년 07월 31일 Thursday",
          "조사자": "조정수",
          "출장일자": "25/08/01",
          "출장목적": "DA251-073112;(협동조합 담보)",
          "출장지역": "서울특별시 서초구 신원동 159",
          "비고": "시내"
        },
      {
          "순번": "9",
          "구분": "(소속평가사·직원)",
          "기간": "2025-07-31",
          "제목": "2025년 07월 31일 Thursday",
          "조사자": "윤권채",
          "출장일자": "25/08/01",
          "출장목적": "DA251-073119-26;(협동조합 담보)",
          "출장지역": "경기도 안성시 계동 161-2",
          "비고": "시외"
        },
      {
          "순번": "10",
          "구분": "(소속평가사·직원)",
          "기간": "2025-07-31",
          "제목": "2025년 07월 31일 Thursday",
          "조사자": "윤권채",
          "출장일자": "25/08/01",
          "출장목적": "DA251-073119-37;(협동조합 담보)",
          "출장지역": "경기도 안성시 보개면 내방리 197 외",
          "비고": "시내"
        }
    ],
    "출장결제" : 
    [
      {
      "결재": "이사",
      "인장": "01-2025.jpg"
    },
    {
      "결재": "이사",
      "인장": "01-2025.jpg"
    },
    {
      "결재": "이사",
      "인장": "01-2025.jpg"
    },
    {
      "결재": "이사",
      "인장": "01-2025.jpg"
    },
    {
      "결재": "이사",
      "인장": "01-2025.jpg"
    },
    {
      "결재": "이사",
      "인장": "01-2025.jpg"
    },
    {
      "결재": "이사",
      "인장": "01-2025.jpg"
    },
    {
      "결재": "이사",
      "인장": "01-2025.jpg"
    },
    {
      "결재": "이사",
      "인장": "01-2025.jpg"
    },
    {
      "결재": "이사",
      "인장": "01-2025.jpg"
    },
    {
      "결재": "이사",
      "인장": "01-2025.jpg"
    },
    {
      "결재": "이사",
      "인장": "01-2025.jpg"
    }
  ]
  }
}